{
  "resourceType": "Observation",
  "id": "Rechtsatrialer-Druck",
  "meta": {
    "profile": [
      "https://www.medizininformatik-initiative.de/fhir/ext/modul-icu/StructureDefinition/scores/StructureDefinition/sd-mii-icu-rechtsatrialer-druck"
    ]
  },
  "code": {
    "coding": [
      {
        "code": "276755008",
        "system": "http://snomed.info/sct",
        "display": "Right atrial pressure (observable entity)"
      },
      {
        "code": "60996-6",
        "system": "http://loinc.org",
        "display": "Right atrial pressure"
      },
      {
        "code": "75367002",
        "system": "http://snomed.info/sct"
      }
    ]
  },
  "component": [
    {
      "code": {
        "coding": [
          {
            "code": "8480-6",
            "system": "http://loinc.org"
          },
          {
            "code": "60998-2",
            "system": "http://loinc.org",
            "display": "Right atrial pressure Systolic"
          }
        ]
      },
      "valueQuantity": {
        "value": 5,
        "code": "mm[Hg]",
        "system": "http://unitsofmeasure.org",
        "unit": "millimeter Mercury column"
      }
    },
    {
      "code": {
        "coding": [
          {
            "code": "8478-0",
            "system": "http://loinc.org"
          },
          {
            "code": "8400-4",
            "system": "http://loinc.org",
            "display": "Right atrial Intrachamber mean pressure"
          }
        ]
      },
      "valueQuantity": {
        "value": 4,
        "code": "mm[Hg]",
        "system": "http://unitsofmeasure.org",
        "unit": "millimeter Mercury column"
      }
    },
    {
      "code": {
        "coding": [
          {
            "code": "8462-4",
            "system": "http://loinc.org"
          },
          {
            "code": "60997-4",
            "system": "http://loinc.org",
            "display": "Right atrial pressure Diastolic"
          }
        ]
      },
      "valueQuantity": {
        "value": 3,
        "code": "mm[Hg]",
        "system": "http://unitsofmeasure.org",
        "unit": "millimeter Mercury column"
      }
    }
  ],
  "status": "final",
  "subject": {
    "reference": "PatientinMusterfrau"
  },
  "effectiveDateTime": "2019-12-23T09:30:10+01:00"
}
