<?xml version="1.0" encoding="utf-8"?>
<StructureDefinition xmlns="http://hl7.org/fhir">
  <id value="Profile-Koerpertemperatur-Kern" />
  <url value="https://medizininformatik-initiative.de/fhir/ext/modul-icu/StructureDefinition/Koerpertemperatur-Kern" />
  <name value="MII_Koerpertemperatur_Kern" />
  <status value="active" />
  <fhirVersion value="4.0.1" />
  <kind value="resource" />
  <abstract value="false" />
  <type value="Observation" />
  <baseDefinition value="https://medizininformatik-initiative.de/fhir/ext/modul-icu/StructureDefinition/Monitoring-und-Vitaldaten" />
  <derivation value="constraint" />
  <differential>
    <element id="Observation.code.coding:loinc">
      <path value="Observation.code.coding" />
      <sliceName value="loinc" />
      <patternCoding>
        <code value="8329-5" />
      </patternCoding>
    </element>
    <element id="Observation.code.coding:IEEE-11073">
      <path value="Observation.code.coding" />
      <sliceName value="IEEE-11073" />
      <patternCoding>
        <code value="150368" />
      </patternCoding>
    </element>
    <element id="Observation.value[x]:valueQuantity">
      <path value="Observation.value[x]" />
      <sliceName value="valueQuantity" />
      <patternQuantity>
        <unit value="degree Celsius" />
        <system value="http://unitsofmeasure.org" />
        <code value="Cel" />
      </patternQuantity>
    </element>
  </differential>
</StructureDefinition>
